{
	"info": {
		"_postman_id": "e14d18da-98e4-446c-82ba-6681a5e59890",
		"name": "IDZ",
		"schema": "https://schema.getpostman.com/json/collection/v2.1.0/collection.json",
		"_exporter_id": "40396075"
	},
	"item": [
		{
			"name": "New Request",
			"request": {
				"method": "GET",
				"header": [],
				"url": {
					"raw": "http://127.0.0.1:5000/api/users",
					"protocol": "http",
					"host": [
						"127",
						"0",
						"0",
						"1"
					],
					"port": "5000",
					"path": [
						"api",
						"users"
					]
				}
			},
			"response": []
		},
		{
			"name": "New Request",
			"request": {
				"method": "POST",
				"header": [],
				"body": {
					"mode": "raw",
					"raw": "{\r\n    \"name\": \"Alice\",\r\n    \"email\": \"alice@example.com\"\r\n}",
					"options": {
						"raw": {
							"language": "json"
						}
					}
				},
				"url": {
					"raw": "http://127.0.0.1:5000/api/users",
					"protocol": "http",
					"host": [
						"127",
						"0",
						"0",
						"1"
					],
					"port": "5000",
					"path": [
						"api",
						"users"
					]
				}
			},
			"response": []
		}
	]
}